crestone/__init__.py
crestone/cli.py
crestone/commands/__init__.py
crestone/commands/configure.py
crestone/commands/deploy.py
crestone/commands/run.py
crestone/tests/__init__.py
crestone-0.1.0.dist-info/LICENSE
crestone-0.1.0.dist-info/METADATA
crestone-0.1.0.dist-info/WHEEL
crestone-0.1.0.dist-info/entry_points.txt
crestone-0.1.0.dist-info/top_level.txt
crestone-0.1.0.dist-info/RECORD
