Metadata-Version: 2.1
Name: crestone
Version: 0.1.0
Summary: A CLI app for Crestone
Home-page: https://github.com/jacobweiss2305/crestone
Author: Jacob Weiss
Author-email: jaweiss2305@gmail.com
Classifier: Development Status :: 3 - Alpha
Classifier: Intended Audience :: Developers
Classifier: License :: OSI Approved :: MIT License
Classifier: Programming Language :: Python :: 3
Classifier: Programming Language :: Python :: 3.7
Classifier: Programming Language :: Python :: 3.8
Classifier: Programming Language :: Python :: 3.9
Requires-Python: >=3.7
License-File: LICENSE
Requires-Dist: click
